toollib/__init__.py
toollib/autodriver.py
toollib/codec.py
toollib/decorator.py
toollib/guid.py
toollib/kvalue.py
toollib/locker.py
toollib/log.py
toollib/logu.py
toollib/pyd.py
toollib/rediscli.py
toollib/regexp.py
toollib/useragent.py
toollib/validator.py
toollib/common/UnRAR.exe
toollib/common/__init__.py
toollib/common/constor.py
toollib/common/error.py
toollib/common/rarfile.py
toollib/common/zipfile.py
toollib/tcli/__init__.py
toollib/tcli/__main__.py
toollib/tcli/base.py
toollib/tcli/cmder.py
toollib/tcli/helper.py
toollib/tcli/option.py
toollib/tcli/commands/__init__.py
toollib/tcli/commands/_bash.py
toollib/tcli/commands/_docker.py
toollib/tcli/commands/_grpc.py
toollib/tcli/commands/_pkgup.py
toollib/tcli/commands/_pydpack.py
toollib/tcli/commands/_set_conda.py
toollib/tcli/commands/_set_mirrors.py
toollib/tcli/commands/_set_pip.py
toollib/tcli/commands/_set_sshkey.py
toollib/tcli/commands/_snowflake.py
toollib/tcli/commands/plugins/__init__.py
toollib/tcli/commands/plugins/aliyun_mirrors.py
toollib/tcli/commands/plugins/bash_tpl.py
toollib/tcli/commands/plugins/docker-compose.yaml
toollib/tcli/commands/plugins/grpc_tpl.py
toollib/tcli/commands/plugins/set_sshkey.sh
toollib/tcli/commands/plugins/snowflake_service.py
toollib/utils/_Chars.py
toollib/utils/_ConfModel.py
toollib/utils/_RedirectStd12ToNull.py
toollib/utils/_Singleton.py
toollib/utils/_VersionCmper.py
toollib/utils/__init__.py
toollib/utils/_copytree.py
toollib/utils/_decompress.py
toollib/utils/_detect_encoding.py
toollib/utils/_gen_leveldirs.py
toollib/utils/_get_cls_attrs.py
toollib/utils/_home.py
toollib/utils/_listfile.py
toollib/utils/_localip.py
toollib/utils/_map_jsontype.py
toollib/utils/_now2timestamp.py
toollib/utils/_now2timestr.py
toollib/utils/_parse_variable.py
toollib/utils/_pkg_lver.py
toollib/utils/_read_csv.py
toollib/utils/_read_xlsx.py
toollib/utils/_split_csv.py
toollib/utils/_split_xlsx.py
toollib/utils/_sysname.py
toollib/utils/_timerange.py
toollib-2.0.6.dist-info/licenses/LICENSE
toollib-2.0.6.dist-info/METADATA
toollib-2.0.6.dist-info/WHEEL
toollib-2.0.6.dist-info/entry_points.txt
toollib-2.0.6.dist-info/top_level.txt
toollib-2.0.6.dist-info/RECORD
