Metadata-Version: 2.4
Name: toollib
Version: 2.0.6
Summary: This is a tool library.
Author-email: axiner <atpuxiner@163.com>
Project-URL: Homepage, https://github.com/atpuxiner/toollib
Classifier: Programming Language :: Python :: 3.10
Classifier: Operating System :: OS Independent
Requires-Python: >=3.10
License-File: LICENSE
Dynamic: license-file
